Analytics_Store/__init__.py
Analytics_Store/utils.py
analytics_store-0.2.dist-info/METADATA
analytics_store-0.2.dist-info/WHEEL
analytics_store-0.2.dist-info/top_level.txt
analytics_store-0.2.dist-info/RECORD
