Metadata-Version: 2.1
Name: analytics-store
Version: 0.2
Summary: Utility functions for data visualization and model evaluation
Home-page: https://github.com/tfiroze/Analytics_Store
Author: Tehsein
Requires-Dist: pandas
Requires-Dist: numpy
Requires-Dist: matplotlib
Requires-Dist: seaborn
Requires-Dist: scikit-learn
